nyu_caesar_crypt_mar24/__init__.py
nyu_caesar_crypt_mar24/__main__.py
nyu_caesar_crypt_mar24/caesar_crypt.py
nyu_caesar_crypt_mar242024-0.1.6.dist-info/LICENSE
nyu_caesar_crypt_mar242024-0.1.6.dist-info/METADATA
nyu_caesar_crypt_mar242024-0.1.6.dist-info/WHEEL
nyu_caesar_crypt_mar242024-0.1.6.dist-info/entry_points.txt
nyu_caesar_crypt_mar242024-0.1.6.dist-info/top_level.txt
nyu_caesar_crypt_mar242024-0.1.6.dist-info/RECORD
