Metadata-Version: 2.1
Name: nyu_caesar_crypt_mar242024
Version: 0.1.6
Summary: A caesar crypt package
Author-email: Janet Pan <jp6024@nyu.edu>, Isaac Kwon <iok206@nyu.edu>, Alexander Kondratiuk <ak8000@nyu.edu>, Adam Schwartz <ags613@nyu.edu>
Project-URL: Homepage, https://github.com/software-students-spring2024/3-python-package-exercise-ja-ia
Project-URL: Repository, https://github.com/software-students-spring2024/3-python-package-exercise-ja-ia.git
Project-URL: Bug Tracker, https://github.com/software-students-spring2024/3-python-package-exercise-ja-ia/issues
Classifier: Programming Language :: Python :: 3
Classifier: License :: OSI Approved :: GNU General Public License v3 (GPLv3)
Classifier: Operating System :: OS Independent
Requires-Python: >=3
License-File: LICENSE
Provides-Extra: dev
Requires-Dist: pytest ; extra == 'dev'
